SuperQwen/__init__.py
SuperQwen/__main__.py
SuperQwen/Agents/__init__.py
SuperQwen/Agents/backend-architect.md
SuperQwen/Agents/devops-architect.md
SuperQwen/Agents/frontend-architect.md
SuperQwen/Agents/learning-guide.md
SuperQwen/Agents/performance-engineer.md
SuperQwen/Agents/python-expert.md
SuperQwen/Agents/quality-engineer.md
SuperQwen/Agents/refactoring-expert.md
SuperQwen/Agents/requirements-analyst.md
SuperQwen/Agents/root-cause-analyst.md
SuperQwen/Agents/security-engineer.md
SuperQwen/Agents/system-architect.md
SuperQwen/Agents/technical-writer.md
SuperQwen/Commands/__init__.py
SuperQwen/Commands/analyze.toml
SuperQwen/Commands/build.toml
SuperQwen/Commands/cleanup.toml
SuperQwen/Commands/design.toml
SuperQwen/Commands/document.toml
SuperQwen/Commands/estimate.toml
SuperQwen/Commands/explain.toml
SuperQwen/Commands/git.toml
SuperQwen/Commands/help.toml
SuperQwen/Commands/implement.toml
SuperQwen/Commands/improve.toml
SuperQwen/Commands/index.toml
SuperQwen/Commands/load.toml
SuperQwen/Commands/reflect.toml
SuperQwen/Commands/save.toml
SuperQwen/Commands/select-tool.toml
SuperQwen/Commands/test.toml
SuperQwen/Commands/troubleshoot.toml
SuperQwen/Config/__init__.py
SuperQwen/Core/FLAGS.md
SuperQwen/Core/PRINCIPLES.md
SuperQwen/Core/RULES.md
SuperQwen/Core/__init__.py
SuperQwen/MCP/MCP_Context7.md
SuperQwen/MCP/MCP_Magic.md
SuperQwen/MCP/MCP_Morphllm.md
SuperQwen/MCP/MCP_Playwright.md
SuperQwen/MCP/MCP_Sequential.md
SuperQwen/MCP/MCP_Serena.md
SuperQwen/MCP/__init__.py
SuperQwen/MCP/configs/__init__.py
SuperQwen/MCP/configs/context7.json
SuperQwen/MCP/configs/magic.json
SuperQwen/MCP/configs/morphllm.json
SuperQwen/MCP/configs/playwright.json
SuperQwen/MCP/configs/sequential.json
SuperQwen/MCP/configs/serena.json
SuperQwen/Modes/MODE_Brainstorming.md
SuperQwen/Modes/MODE_Introspection.md
SuperQwen/Modes/MODE_Orchestration.md
SuperQwen/Modes/MODE_Task_Management.md
SuperQwen/Modes/MODE_Token_Efficiency.md
SuperQwen/Modes/__init__.py
superqwen-1.0.1.dist-info/licenses/LICENSE
superqwen-1.0.1.dist-info/METADATA
superqwen-1.0.1.dist-info/WHEEL
superqwen-1.0.1.dist-info/entry_points.txt
superqwen-1.0.1.dist-info/top_level.txt
superqwen-1.0.1.dist-info/RECORD
