Metadata-Version: 2.4
Name: SuperQwen
Version: 1.0.1
Summary: An AI-enhanced development framework for Qwen CLI
Author-email: NomenAK <anton.knoery@gmail.com>, Mithun Gowda B <mithungowda.b7411@gmail.com>
License-Expression: MIT
Project-URL: Homepage, https://github.com/SuperClaude-Org/SuperQwen_Framework
Project-URL: Issues, https://github.com/SuperClaude-Org/SuperQwen_Framework/issues
Classifier: Development Status :: 4 - Beta
Classifier: Programming Language :: Python :: 3
Classifier: Operating System :: OS Independent
Classifier: Topic :: Software Development :: Code Generators
Requires-Python: >=3.8
License-File: LICENSE
Requires-Dist: typer[all]
Dynamic: license-file
